datashell_engines-0.1.0.dist-info/METADATA
datashell_engines-0.1.0.dist-info/WHEEL
datashell_engines/__init__.py
datashell_engines/datashell_engines.abi3.so
datashell_engines-0.1.0.dist-info/RECORD
