Metadata-Version: 2.1
Name: datashell-engines
Version: 0.1.0
Summary: Datashell engines rust library
